<Properties StartupConfiguration="{E71DD6BF-F185-4A6D-9228-241B46032F6D}|Default">
  <MonoDevelop.Ide.ItemProperties.DesignPatterns PreferredExecutionTarget="MonoDevelop.Default" />
  <MonoDevelop.Ide.Workbench ActiveDocument="DesignPatterns/Program.cs">
    <Files>
      <File FileName="DesignPatterns/Program.cs" Line="12" Column="33" />
    </Files>
    <Pads>
      <Pad Id="ProjectPad">
        <State name="__root__">
          <Node name="DesignPatterns" expanded="True">
            <Node name="DesignPatterns" expanded="True">
              <Node name="Program.cs" selected="True" />
            </Node>
          </Node>
        </State>
      </Pad>
    </Pads>
  </MonoDevelop.Ide.Workbench>
  <MonoDevelop.Ide.DebuggingService.PinnedWatches />
  <MonoDevelop.Ide.Workspace ActiveConfiguration="Debug|anycpu" />
  <MonoDevelop.Ide.DebuggingService.Breakpoints>
    <BreakpointStore />
  </MonoDevelop.Ide.DebuggingService.Breakpoints>
  <MultiItemStartupConfigurations />
</Properties>